image_input_handler/__init__.py
image_input_handler/image_input_handler.py
image_input_handler-0.4.0.dist-info/METADATA
image_input_handler-0.4.0.dist-info/WHEEL
image_input_handler-0.4.0.dist-info/top_level.txt
image_input_handler-0.4.0.dist-info/RECORD
